ostk/__init__.py
ostk/physics/OpenSpaceToolkitPhysicsPy.cpython-310-aarch64-linux-gnu.so
ostk/physics/__init__.py
ostk/physics/__init__.pyi
ostk/physics/libopen-space-toolkit-physics.so.13
ostk/physics/time.pyi
ostk/physics/unit.pyi
ostk/physics/coordinate/__init__.pyi
ostk/physics/coordinate/spherical.pyi
ostk/physics/coordinate/frame/__init__.pyi
ostk/physics/coordinate/frame/provider/__init__.pyi
ostk/physics/coordinate/frame/provider/iau.pyi
ostk/physics/coordinate/frame/provider/iers.pyi
ostk/physics/data/__init__.pyi
ostk/physics/data/provider.pyi
ostk/physics/environment/__init__.pyi
ostk/physics/environment/utility.pyi
ostk/physics/environment/atmospheric/__init__.pyi
ostk/physics/environment/atmospheric/earth.pyi
ostk/physics/environment/ephemeris/__init__.pyi
ostk/physics/environment/ephemeris/spice.pyi
ostk/physics/environment/gravitational/__init__.pyi
ostk/physics/environment/gravitational/earth.pyi
ostk/physics/environment/magnetic/__init__.pyi
ostk/physics/environment/magnetic/earth.pyi
ostk/physics/environment/object/__init__.pyi
ostk/physics/environment/object/celestial/__init__.pyi
ostk/physics/environment/object/celestial/moon.pyi
ostk/physics/environment/object/celestial/sun.pyi
ostk/physics/test/__init__.py
ostk/physics/test/test_environment.py
ostk/physics/test/test_import.py
ostk/physics/test/coordinate/__init__.py
ostk/physics/test/coordinate/test_axes.py
ostk/physics/test/coordinate/test_frame.py
ostk/physics/test/coordinate/test_position.py
ostk/physics/test/coordinate/test_transform.py
ostk/physics/test/coordinate/test_velocity.py
ostk/physics/test/coordinate/frame/__init__.py
ostk/physics/test/coordinate/frame/provider/__init__.py
ostk/physics/test/coordinate/frame/provider/iers/__init__.py
ostk/physics/test/coordinate/frame/provider/iers/conftest.py
ostk/physics/test/coordinate/frame/provider/iers/test_bulletin_a.py
ostk/physics/test/coordinate/frame/provider/iers/test_finals_2000a.py
open_space_toolkit_physics-13.3.0.dist-info/METADATA
open_space_toolkit_physics-13.3.0.dist-info/WHEEL
open_space_toolkit_physics-13.3.0.dist-info/top_level.txt
open_space_toolkit_physics-13.3.0.dist-info/zip-safe
open_space_toolkit_physics-13.3.0.dist-info/RECORD
