Metadata-Version: 2.2
Name: open-space-toolkit-physics
Version: 13.3.0
Summary: Physical units, time, reference frames, environment modeling.
Author: Open Space Collective
Author-email: contact@open-space-collective.org
License: Apache License 2.0
Keywords: open-space-collective,open-space-toolkit physics
Classifier: Development Status :: 3 - Alpha
Classifier: Programming Language :: Python :: 3
Classifier: License :: OSI Approved :: Apache Software License
Classifier: Operating System :: POSIX :: Linux
Requires-Dist: open-space-toolkit-core~=5.0
Requires-Dist: open-space-toolkit-io~=4.0
Requires-Dist: open-space-toolkit-mathematics~=4.3
